MANIFEST.in
README.rst
setup.py
yahoo_finance/__init__.py
yahoo_finance/yql.py
yahoo_finance.egg-info/PKG-INFO
yahoo_finance.egg-info/SOURCES.txt
yahoo_finance.egg-info/dependency_links.txt
yahoo_finance.egg-info/entry_points.txt
yahoo_finance.egg-info/requires.txt
yahoo_finance.egg-info/top_level.txt