Metadata-Version: 1.1
Name: yahoo-finance
Version: 1.1.4
Summary: Python module to get stock data from Yahoo! Finance
Home-page: https://github.com/lukaszbanasiak/yahoo-finance
Author: Lukasz Banasiak
Author-email: lukasz@banasiak.me
License: MIT
Download-URL: https://github.com/lukaszbanasiak/yahoo-finance/releases
Keywords: stocks market finance yahoo quotes shares currency
Platform: UNKNOWN
Classifier: Development Status :: 5 - Production/Stable
Classifier: Intended Audience :: Developers
Classifier: Intended Audience :: Financial and Insurance Industry
Classifier: Topic :: Office/Business :: Financial :: Investment
Classifier: Topic :: Software Development :: Libraries :: Python Modules
Classifier: Operating System :: OS Independent
Classifier: License :: OSI Approved :: MIT License
Classifier: Programming Language :: Python :: 2
Classifier: Programming Language :: Python :: 2.6
Classifier: Programming Language :: Python :: 2.7
